bole/.version
bole/__init__.py
bole/__main__.py
bole/cli.py
bole/cli_options.py
bole/consts.py
bole/exceptions.py
bole/format.py
bole/log.py
bole/utils.py
bole/config/__init__.py
bole/config/built_in.py
bole/config/cascading.py
bole/config/dict.py
bole-0.0.13.dist-info/LICENSE
bole-0.0.13.dist-info/METADATA
bole-0.0.13.dist-info/WHEEL
bole-0.0.13.dist-info/entry_points.txt
bole-0.0.13.dist-info/top_level.txt
bole-0.0.13.dist-info/RECORD
