Metadata-Version: 2.1
Name: bole
Version: 0.0.13
Summary: Cascading configuration manager and logger for python (yaml, json)
Home-page: https://github.com/LamaAni/bole
Author: Zav Shotan
License: UNKNOWN
Project-URL: Source, https://github.com/LamaAni/bole
Keywords: configuration config log yaml json
Platform: UNKNOWN
License-File: LICENSE
Requires-Dist: click (==8.1.3)
Requires-Dist: pyyaml (==6.0)
